nionswift_io-15.5.0.dist-info/licenses/LICENSE
nionswift_plugin/DM_IO/__init__.py
nionswift_plugin/DM_IO/dm3_image_utils.py
nionswift_plugin/DM_IO/parse_dm3.py
nionswift_plugin/DM_IO/test/__init__.py
nionswift_plugin/DM_IO/test/dm3parser_test.py
nionswift_plugin/DM_IO/test/resources/ref_F_0_1.dm3
nionswift_plugin/DM_IO/test/resources/ref_F_0_1.dm4
nionswift_plugin/DM_IO/test/resources/ref_F_0_2.dm3
nionswift_plugin/DM_IO/test/resources/ref_F_0_2.dm4
nionswift_plugin/DM_IO/test/resources/ref_F_1_1.dm3
nionswift_plugin/DM_IO/test/resources/ref_F_1_1.dm4
nionswift_plugin/DM_IO/test/resources/ref_F_1_2.dm3
nionswift_plugin/DM_IO/test/resources/ref_F_1_2.dm4
nionswift_plugin/DM_IO/test/resources/ref_F_2_1.dm3
nionswift_plugin/DM_IO/test/resources/ref_F_2_1.dm4
nionswift_plugin/DM_IO/test/resources/ref_T_0_1.dm3
nionswift_plugin/DM_IO/test/resources/ref_T_0_1.dm4
nionswift_plugin/DM_IO/test/resources/ref_T_0_2.dm3
nionswift_plugin/DM_IO/test/resources/ref_T_0_2.dm4
nionswift_plugin/TIFF_IO/__init__.py
nionswift_plugin/TIFF_IO/test/TIFF_test.py
nionswift_plugin/TIFF_IO/test/__init__.py
nionswift_io-15.5.0.dist-info/METADATA
nionswift_io-15.5.0.dist-info/WHEEL
nionswift_io-15.5.0.dist-info/top_level.txt
nionswift_io-15.5.0.dist-info/RECORD
