Metadata-Version: 2.4
Name: nionswift-io
Version: 15.5.0
Summary: NionSwift IO handlers.
Home-page: https://github.com/nion-software/nionswift-io
Author: Nion Software
Author-email: swift@nion.com
License: Apache-2.0
Classifier: Development Status :: 5 - Production/Stable
Classifier: License :: OSI Approved :: Apache Software License
Classifier: Programming Language :: Python :: 3.11
Classifier: Programming Language :: Python :: 3.12
Classifier: Programming Language :: Python :: 3.13
Requires-Python: >=3.11
License-File: LICENSE
Requires-Dist: niondata<16.0,>=15.8
Requires-Dist: nionutils<5.0,>=4.13
Requires-Dist: numpy<3.0,>=2.0
Requires-Dist: pytz
Requires-Dist: tifffile
Dynamic: license-file
